{"lastUsed":1669059332798,"path":"A:\/1dam\/1dam\/ECÑLIPSE\/eclipse-workspace","projectCount":10,"recentFiles":[{"path":"\/practicas60\/src\/practicas60","parentWorkspace":"C:\/Users\/1ASIR\/eclipse-workspace","name":"practica11.java","lastModified":1666291774754,"locationURI":"file:\/C:\/Users\/1ASIR\/eclipse-workspace\/practicas60\/src\/practicas60\/practica11.java"},{"path":"\/practicas60\/src\/practicas60","parentWorkspace":"C:\/Users\/1ASIR\/Desktop\/1dam\/ECÑLIPSE\/eclipse-workspace","name":"practica27.java","lastModified":1668015647334,"locationURI":"file:\/C:\/Users\/1ASIR\/Desktop\/1dam\/ECÑLIPSE\/eclipse-workspace\/practicas60\/src\/practicas60\/practica27.java"},{"path":"\/practicas60\/src\/practicas60","parentWorkspace":"C:\/Users\/1ASIR\/Desktop\/1dam\/ECÑLIPSE\/eclipse-workspace","name":"practica32.java","lastModified":1668015647334,"locationURI":"file:\/C:\/Users\/1ASIR\/Desktop\/1dam\/ECÑLIPSE\/eclipse-workspace\/practicas60\/src\/practicas60\/practica32.java"},{"path":"\/programación\/src\/programación","parentWorkspace":"C:\/Users\/1ASIR\/eclipse-workspace","name":"practica17.java","lastModified":1666360585677,"locationURI":"file:\/C:\/Users\/1ASIR\/eclipse-workspace\/programación\/src\/programación\/practica17.java"},{"path":"\/hola\/src\/hola","parentWorkspace":"C:\/Users\/1ASIR\/Desktop\/1dam\/ECÑLIPSE\/eclipse-workspace","name":"prueba.java","lastModified":1668627806857,"locationURI":"file:\/C:\/Users\/1ASIR\/Desktop\/1dam\/ECÑLIPSE\/eclipse-workspace\/hola\/src\/hola\/prueba.java"},{"path":"\/practicas60\/src\/practicas60","parentWorkspace":"C:\/Users\/1ASIR\/eclipse-workspace","name":"practica5.java","lastModified":1666202791485,"locationURI":"file:\/C:\/Users\/1ASIR\/eclipse-workspace\/practicas60\/src\/practicas60\/practica5.java"},{"path":"\/practica4mejor\/src\/practica4mejor","parentWorkspace":"C:\/Users\/1ASIR\/eclipse-workspace","name":"practica4mejor.java"},{"path":"\/practicas60\/src\/practicas60","parentWorkspace":"G:\/cosas\/eclipse\/eclipse-workspace","name":"practica18.java","lastModified":1666782958836,"locationURI":"file:\/G:\/cosas\/eclipse\/eclipse-workspace\/practicas60\/src\/practicas60\/practica18.java"},{"path":"\/practicas60\/src\/practicas60","parentWorkspace":"C:\/Users\/1ASIR\/Desktop\/1dam\/ECÑLIPSE\/eclipse-workspace","name":"practica23.java","lastModified":1667497553460,"locationURI":"file:\/C:\/Users\/1ASIR\/Desktop\/1dam\/ECÑLIPSE\/eclipse-workspace\/practicas60\/src\/practicas60\/practica23.java"},{"path":"\/programación\/src\/programación","parentWorkspace":"C:\/Users\/1ASIR\/eclipse-workspace","name":"practica13.java","lastModified":1666360387561,"locationURI":"file:\/C:\/Users\/1ASIR\/eclipse-workspace\/programación\/src\/programación\/practica13.java"},{"path":"\/practicas60\/src\/practicas60","parentWorkspace":"C:\/Users\/1ASIR\/Desktop\/1dam\/ECÑLIPSE\/eclipse-workspace","name":"practica39.java","lastModified":1668110263857,"locationURI":"file:\/C:\/Users\/1ASIR\/Desktop\/1dam\/ECÑLIPSE\/eclipse-workspace\/practicas60\/src\/practicas60\/practica39.java"},{"path":"\/practicas60\/src\/practicas60","parentWorkspace":"A:\/1dam\/1dam\/ECÑLIPSE\/eclipse-workspace","name":"practica44.java","lastModified":1669058193137,"locationURI":"file:\/A:\/1dam\/1dam\/ECÑLIPSE\/eclipse-workspace\/practicas60\/src\/practicas60\/practica44.java"},{"path":"\/programación\/src\/programación","parentWorkspace":"C:\/Users\/1ASIR\/eclipse-workspace","name":"practica10.java","lastModified":1666359714024,"locationURI":"file:\/C:\/Users\/1ASIR\/eclipse-workspace\/programación\/src\/programación\/practica10.java"},{"path":"\/practicas60\/src\/practicas60","parentWorkspace":"C:\/Users\/1ASIR\/Desktop\/1dam\/ECÑLIPSE\/eclipse-workspace","name":"practica36.java","lastModified":1668110263857,"locationURI":"file:\/C:\/Users\/1ASIR\/Desktop\/1dam\/ECÑLIPSE\/eclipse-workspace\/practicas60\/src\/practicas60\/practica36.java"},{"path":"\/practicas60\/src\/practicas60","parentWorkspace":"C:\/Users\/1ASIR\/Desktop\/1dam\/ECÑLIPSE\/eclipse-workspace","name":"practica41.java","lastModified":1668709896684,"locationURI":"file:\/C:\/Users\/1ASIR\/Desktop\/1dam\/ECÑLIPSE\/eclipse-workspace\/practicas60\/src\/practicas60\/practica41.java"},{"path":"\/practicas60\/src\/practicas60","parentWorkspace":"C:\/Users\/1ASIR\/Desktop\/1dam\/ECÑLIPSE\/eclipse-workspace","name":"practica29entregar.java","lastModified":1668103240406,"locationURI":"file:\/C:\/Users\/1ASIR\/Desktop\/1dam\/ECÑLIPSE\/eclipse-workspace\/practicas60\/src\/practicas60\/practica29entregar.java"},{"path":"\/practicas60\/src\/practicas60","parentWorkspace":"C:\/Users\/1ASIR\/Desktop\/1dam\/ECÑLIPSE\/eclipse-workspace","name":"practica35.java","lastModified":1668707004170,"locationURI":"file:\/C:\/Users\/1ASIR\/Desktop\/1dam\/ECÑLIPSE\/eclipse-workspace\/practicas60\/src\/practicas60\/practica35.java"},{"path":"\/practicas60\/src\/practicas60","parentWorkspace":"C:\/Users\/1ASIR\/eclipse-workspace","name":"practica9.java","lastModified":1666287513880,"locationURI":"file:\/C:\/Users\/1ASIR\/eclipse-workspace\/practicas60\/src\/practicas60\/practica9.java"},{"path":"\/hola\/src\/hola","parentWorkspace":"A:\/1dam\/1dam\/ECÑLIPSE\/eclipse-workspace","name":"protos.java","lastModified":1668708582655,"locationURI":"file:\/A:\/1dam\/1dam\/ECÑLIPSE\/eclipse-workspace\/hola\/src\/hola\/protos.java"},{"path":"\/practicas60\/src\/practicas60","parentWorkspace":"C:\/Users\/1ASIR\/eclipse-workspace","name":"practica8.java","lastModified":1666287142685,"locationURI":"file:\/C:\/Users\/1ASIR\/eclipse-workspace\/practicas60\/src\/practicas60\/practica8.java"},{"path":"\/programación\/src\/programación","parentWorkspace":"C:\/Users\/1ASIR\/eclipse-workspace","name":"practica18.java","lastModified":1666360617024,"locationURI":"file:\/C:\/Users\/1ASIR\/eclipse-workspace\/programación\/src\/programación\/practica18.java"},{"path":"\/programación\/src\/programación","parentWorkspace":"C:\/Users\/1ASIR\/eclipse-workspace","name":"practica3.java","lastModified":1666359331580,"locationURI":"file:\/C:\/Users\/1ASIR\/eclipse-workspace\/programación\/src\/programación\/practica3.java"},{"path":"\/practicas60\/src\/practicas60","parentWorkspace":"C:\/Users\/1ASIR\/Desktop\/1dam\/ECÑLIPSE\/eclipse-workspace","name":"practica33.java","lastModified":1668015647334,"locationURI":"file:\/C:\/Users\/1ASIR\/Desktop\/1dam\/ECÑLIPSE\/eclipse-workspace\/practicas60\/src\/practicas60\/practica33.java"},{"path":"\/practicapqmesaledelabola\/src\/practicapqmesaledelabola","parentWorkspace":"C:\/Users\/1ASIR\/eclipse-workspace","name":"uwu.java"},{"path":"\/bucleFor\/src\/bucleFor","parentWorkspace":"C:\/Users\/1ASIR\/eclipse-workspace","name":"bucleFor.java"},{"path":"\/entorno\/src\/entorno","parentWorkspace":"A:\/1dam\/1dam\/ECÑLIPSE\/eclipse-workspace","name":"abrbrbr.java","lastModified":1669058192366,"locationURI":"file:\/A:\/1dam\/1dam\/ECÑLIPSE\/eclipse-workspace\/entorno\/src\/entorno\/abrbrbr.java"},{"path":"\/practicas60\/src\/practicas60","parentWorkspace":"C:\/Users\/1ASIR\/Desktop\/1dam\/ECÑLIPSE\/eclipse-workspace","name":"practica31.java","lastModified":1668015647334,"locationURI":"file:\/C:\/Users\/1ASIR\/Desktop\/1dam\/ECÑLIPSE\/eclipse-workspace\/practicas60\/src\/practicas60\/practica31.java"},{"path":"\/practicaSorpresa1\/src\/practicaSorpresa1","parentWorkspace":"C:\/Users\/1ASIR\/eclipse-workspace","name":"practicaSorpresa1.java"},{"path":"\/practicas60\/src\/practicas60","parentWorkspace":"C:\/Users\/1ASIR\/eclipse-workspace","name":"practica6.java","lastModified":1666287527112,"locationURI":"file:\/C:\/Users\/1ASIR\/eclipse-workspace\/practicas60\/src\/practicas60\/practica6.java"},{"path":"\/programación\/src\/programación","parentWorkspace":"C:\/Users\/1ASIR\/eclipse-workspace","name":"practica16.java","lastModified":1666795273272,"locationURI":"file:\/C:\/Users\/1ASIR\/eclipse-workspace\/programación\/src\/programación\/practica16.java"},{"path":"\/practicas60\/src\/practicas60","parentWorkspace":"C:\/Users\/1ASIR\/eclipse-workspace","name":"practica4.java","lastModified":1666202454665,"locationURI":"file:\/C:\/Users\/1ASIR\/eclipse-workspace\/practicas60\/src\/practicas60\/practica4.java"},{"path":"\/programación\/src\/programación","parentWorkspace":"C:\/Users\/1ASIR\/eclipse-workspace","name":"practica14.java","lastModified":1666360432015,"locationURI":"file:\/C:\/Users\/1ASIR\/eclipse-workspace\/programación\/src\/programación\/practica14.java"},{"path":"\/practicas60\/src\/practicas60","parentWorkspace":"G:\/cosas\/eclipse\/eclipse-workspace","name":"practica19.java","lastModified":1666783294514,"locationURI":"file:\/G:\/cosas\/eclipse\/eclipse-workspace\/practicas60\/src\/practicas60\/practica19.java"},{"path":"\/practicas60\/src\/practicas60","parentWorkspace":"C:\/Users\/1ASIR\/eclipse-workspace","name":"practica2.java","lastModified":1666201858078,"locationURI":"file:\/C:\/Users\/1ASIR\/eclipse-workspace\/practicas60\/src\/practicas60\/practica2.java"},{"path":"\/practicas60\/src\/practicas60","parentWorkspace":"G:\/cosas\/eclipse\/eclipse-workspace","name":"practica17.java","lastModified":1666791067586,"locationURI":"file:\/G:\/cosas\/eclipse\/eclipse-workspace\/practicas60\/src\/practicas60\/practica17.java"},{"path":"\/programación\/src\/programación","parentWorkspace":"C:\/Users\/1ASIR\/eclipse-workspace","name":"practica9.java","lastModified":1666359681261,"locationURI":"file:\/C:\/Users\/1ASIR\/eclipse-workspace\/programación\/src\/programación\/practica9.java"},{"path":"\/practicas60\/src\/practicas60","parentWorkspace":"C:\/Users\/1ASIR\/Desktop\/1dam\/ECÑLIPSE\/eclipse-workspace","name":"practica21.java","lastModified":1667399680644,"locationURI":"file:\/C:\/Users\/1ASIR\/Desktop\/1dam\/ECÑLIPSE\/eclipse-workspace\/practicas60\/src\/practicas60\/practica21.java"},{"path":"\/practica5mejor\/src\/practica5mejor","parentWorkspace":"C:\/Users\/1ASIR\/eclipse-workspace","name":"practica5mejor.java"},{"path":"\/practicas60\/src\/practicas60","parentWorkspace":"G:\/cosas\/eclipse\/eclipse-workspace","name":"practica15.java","lastModified":1667497553460,"locationURI":"file:\/G:\/cosas\/eclipse\/eclipse-workspace\/practicas60\/src\/practicas60\/practica15.java"},{"path":"\/programación\/src\/programación","parentWorkspace":"C:\/Users\/1ASIR\/eclipse-workspace","name":"practica7.java","lastModified":1666359466186,"locationURI":"file:\/C:\/Users\/1ASIR\/eclipse-workspace\/programación\/src\/programación\/practica7.java"},{"path":"\/practicas60\/src\/practicas60","parentWorkspace":"C:\/Users\/1ASIR\/eclipse-workspace","name":"practica13.java","lastModified":1666779225109,"locationURI":"file:\/C:\/Users\/1ASIR\/eclipse-workspace\/practicas60\/src\/practicas60\/practica13.java"},{"path":"\/entorno\/src\/entorno","parentWorkspace":"C:\/Users\/1ASIR\/Desktop\/1dam\/ECÑLIPSE\/eclipse-workspace","name":"ascensor.java","lastModified":1669058192366,"locationURI":"file:\/C:\/Users\/1ASIR\/Desktop\/1dam\/ECÑLIPSE\/eclipse-workspace\/entorno\/src\/entorno\/ascensor.java"},{"path":"\/programación\/src\/programación","parentWorkspace":"C:\/Users\/1ASIR\/eclipse-workspace","name":"practica5.java","lastModified":1666359392272,"locationURI":"file:\/C:\/Users\/1ASIR\/eclipse-workspace\/programación\/src\/programación\/practica5.java"},{"path":"\/programación\/src\/programación","parentWorkspace":"C:\/Users\/1ASIR\/eclipse-workspace","name":"practica19.java","lastModified":1666360647880,"locationURI":"file:\/C:\/Users\/1ASIR\/eclipse-workspace\/programación\/src\/programación\/practica19.java"},{"path":"\/practicas60\/src\/practicas60","parentWorkspace":"C:\/Users\/1ASIR\/Desktop\/1dam\/ECÑLIPSE\/eclipse-workspace","name":"practica29.java","lastModified":1668707004170,"locationURI":"file:\/C:\/Users\/1ASIR\/Desktop\/1dam\/ECÑLIPSE\/eclipse-workspace\/practicas60\/src\/practicas60\/practica29.java"},{"path":"\/practicas60\/src\/practicas60","parentWorkspace":"C:\/Users\/1ASIR\/Desktop\/1dam\/ECÑLIPSE\/eclipse-workspace","name":"praactica32Array.java","lastModified":1668707004170,"locationURI":"file:\/C:\/Users\/1ASIR\/Desktop\/1dam\/ECÑLIPSE\/eclipse-workspace\/practicas60\/src\/practicas60\/praactica32Array.java"},{"path":"\/practicas60\/src\/practicas60","parentWorkspace":"C:\/Users\/1ASIR\/Desktop\/1dam\/ECÑLIPSE\/eclipse-workspace","name":"practica34.java","lastModified":1668707004170,"locationURI":"file:\/C:\/Users\/1ASIR\/Desktop\/1dam\/ECÑLIPSE\/eclipse-workspace\/practicas60\/src\/practicas60\/practica34.java"},{"path":"\/practicas60\/src\/practicas60","parentWorkspace":"C:\/Users\/1ASIR\/eclipse-workspace","name":"practica7.java","lastModified":1666286602451,"locationURI":"file:\/C:\/Users\/1ASIR\/eclipse-workspace\/practicas60\/src\/practicas60\/practica7.java"},{"path":"\/programación\/src\/programación","parentWorkspace":"C:\/Users\/1ASIR\/eclipse-workspace","name":"practica2.java","lastModified":1666359304650,"locationURI":"file:\/C:\/Users\/1ASIR\/eclipse-workspace\/programación\/src\/programación\/practica2.java"},{"path":"\/programación\/src\/programación","parentWorkspace":"C:\/Users\/1ASIR\/eclipse-workspace","name":"practica15.java","lastModified":1666360470084,"locationURI":"file:\/C:\/Users\/1ASIR\/eclipse-workspace\/programación\/src\/programación\/practica15.java"},{"path":"\/practicas60\/src\/practicas60","parentWorkspace":"G:\/cosas\/eclipse\/eclipse-workspace","name":"practica25.java","lastModified":1667497553460,"locationURI":"file:\/G:\/cosas\/eclipse\/eclipse-workspace\/practicas60\/src\/practicas60\/practica25.java"},{"path":"\/practicas60\/src\/practicas60","parentWorkspace":"C:\/Users\/1ASIR\/Desktop\/1dam\/ECÑLIPSE\/eclipse-workspace","name":"practica30.java","lastModified":1668015647334,"locationURI":"file:\/C:\/Users\/1ASIR\/Desktop\/1dam\/ECÑLIPSE\/eclipse-workspace\/practicas60\/src\/practicas60\/practica30.java"},{"path":"\/practicas60\/src\/practicas60","parentWorkspace":"C:\/Users\/1ASIR\/eclipse-workspace","name":"practica3.java","lastModified":1666202078921,"locationURI":"file:\/C:\/Users\/1ASIR\/eclipse-workspace\/practicas60\/src\/practicas60\/practica3.java"},{"path":"\/practicas60\/src\/practicas60","parentWorkspace":"A:\/1dam\/1dam\/ECÑLIPSE\/eclipse-workspace","name":"practica46.java","lastModified":1669058193137,"locationURI":"file:\/A:\/1dam\/1dam\/ECÑLIPSE\/eclipse-workspace\/practicas60\/src\/practicas60\/practica46.java"},{"path":"\/practicaPrueba\/src\/practicaPrueba","parentWorkspace":"C:\/Users\/1ASIR\/eclipse-workspace","name":"pruebaPractica.java"},{"path":"\/programación\/src\/programación","parentWorkspace":"C:\/Users\/1ASIR\/eclipse-workspace","name":"practica11.java","lastModified":1666359750789,"locationURI":"file:\/C:\/Users\/1ASIR\/eclipse-workspace\/programación\/src\/programación\/practica11.java"},{"path":"\/practicas60\/src\/practicas60","parentWorkspace":"C:\/Users\/1ASIR\/Desktop\/1dam\/ECÑLIPSE\/eclipse-workspace","name":"a.java","lastModified":1668617722848,"locationURI":"file:\/C:\/Users\/1ASIR\/Desktop\/1dam\/ECÑLIPSE\/eclipse-workspace\/practicas60\/src\/practicas60\/a.java"},{"path":"\/practicas60\/src\/practicas60","parentWorkspace":"C:\/Users\/1ASIR\/Desktop\/1dam\/ECÑLIPSE\/eclipse-workspace","name":"practica38.java","lastModified":1668110263857,"locationURI":"file:\/C:\/Users\/1ASIR\/Desktop\/1dam\/ECÑLIPSE\/eclipse-workspace\/practicas60\/src\/practicas60\/practica38.java"},{"path":"\/practicas60\/src\/practicas60","parentWorkspace":"A:\/1dam\/1dam\/ECÑLIPSE\/eclipse-workspace","name":"practica43.java","lastModified":1669058193137,"locationURI":"file:\/A:\/1dam\/1dam\/ECÑLIPSE\/eclipse-workspace\/practicas60\/src\/practicas60\/practica43.java"},{"path":"\/practicas60\/src\/practicas60","parentWorkspace":"C:\/Users\/1ASIR\/Desktop\/1dam\/ECÑLIPSE\/eclipse-workspace","name":"practica37.java","lastModified":1668106423675,"locationURI":"file:\/C:\/Users\/1ASIR\/Desktop\/1dam\/ECÑLIPSE\/eclipse-workspace\/practicas60\/src\/practicas60\/practica37.java"},{"path":"\/practicas60\/src\/practicas60","parentWorkspace":"C:\/Users\/1ASIR\/Desktop\/1dam\/ECÑLIPSE\/eclipse-workspace","name":"practica42.java","lastModified":1668707004170,"locationURI":"file:\/C:\/Users\/1ASIR\/Desktop\/1dam\/ECÑLIPSE\/eclipse-workspace\/practicas60\/src\/practicas60\/practica42.java"},{"path":"\/hola\/src\/hola","parentWorkspace":"A:\/1dam\/1dam\/ECÑLIPSE\/eclipse-workspace","name":"a.java","lastModified":1669058193137,"locationURI":"file:\/A:\/1dam\/1dam\/ECÑLIPSE\/eclipse-workspace\/hola\/src\/hola\/a.java"},{"path":"\/practicas60\/src\/practicas60","parentWorkspace":"C:\/Users\/1ASIR\/eclipse-workspace","name":"practica10.java","lastModified":1666288331455,"locationURI":"file:\/C:\/Users\/1ASIR\/eclipse-workspace\/practicas60\/src\/practicas60\/practica10.java"},{"path":"\/practicas60\/src\/practicas60","parentWorkspace":"C:\/Users\/1ASIR\/Desktop\/1dam\/ECÑLIPSE\/eclipse-workspace","name":"practica28.java","lastModified":1668102500447,"locationURI":"file:\/C:\/Users\/1ASIR\/Desktop\/1dam\/ECÑLIPSE\/eclipse-workspace\/practicas60\/src\/practicas60\/practica28.java"},{"path":"\/practicas60\/src\/practicas60","parentWorkspace":"G:\/cosas\/eclipse\/eclipse-workspace","name":"practica26.java","lastModified":1668102500447,"locationURI":"file:\/G:\/cosas\/eclipse\/eclipse-workspace\/practicas60\/src\/practicas60\/practica26.java"},{"path":"\/practicas60\/src\/practicas60","parentWorkspace":"C:\/Users\/1ASIR\/Desktop\/1dam\/ECÑLIPSE\/eclipse-workspace","name":"practica28sergio.java","lastModified":1667501211414,"locationURI":"file:\/C:\/Users\/1ASIR\/Desktop\/1dam\/ECÑLIPSE\/eclipse-workspace\/practicas60\/src\/practicas60\/practica28sergio.java"},{"path":"\/practicas60\/src\/practicas60","parentWorkspace":"C:\/Users\/1ASIR\/Desktop\/1dam\/ECÑLIPSE\/eclipse-workspace","name":"practica24.java","lastModified":1667075511432,"locationURI":"file:\/C:\/Users\/1ASIR\/Desktop\/1dam\/ECÑLIPSE\/eclipse-workspace\/practicas60\/src\/practicas60\/practica24.java"},{"path":"\/practicas60\/src\/practicas60","parentWorkspace":"C:\/Users\/1ASIR\/Desktop\/1dam\/ECÑLIPSE\/eclipse-workspace","name":"practica22.java","lastModified":1667497553460,"locationURI":"file:\/C:\/Users\/1ASIR\/Desktop\/1dam\/ECÑLIPSE\/eclipse-workspace\/practicas60\/src\/practicas60\/practica22.java"},{"path":"\/practicas60\/src\/practicas60","parentWorkspace":"C:\/Users\/1ASIR\/eclipse-workspace","name":"practica16.java","lastModified":1666720226602,"locationURI":"file:\/C:\/Users\/1ASIR\/eclipse-workspace\/practicas60\/src\/practicas60\/practica16.java"},{"path":"\/practicas60\/src\/practicas60","parentWorkspace":"C:\/Users\/1ASIR\/eclipse-workspace","name":"practica1.java","lastModified":1666201088510,"locationURI":"file:\/C:\/Users\/1ASIR\/eclipse-workspace\/practicas60\/src\/practicas60\/practica1.java"},{"path":"\/programación\/src\/programación","parentWorkspace":"C:\/Users\/1ASIR\/eclipse-workspace","name":"practica8.java","lastModified":1666359636243,"locationURI":"file:\/C:\/Users\/1ASIR\/eclipse-workspace\/programación\/src\/programación\/practica8.java"},{"path":"\/practicas60\/src\/practicas60","parentWorkspace":"C:\/Users\/1ASIR\/eclipse-workspace","name":"practica20.java","lastModified":1666720590495,"locationURI":"file:\/C:\/Users\/1ASIR\/eclipse-workspace\/practicas60\/src\/practicas60\/practica20.java"},{"path":"\/practicas60\/src\/practicas60","parentWorkspace":"G:\/cosas\/eclipse\/eclipse-workspace","name":"practica14.java","lastModified":1666781271761,"locationURI":"file:\/G:\/cosas\/eclipse\/eclipse-workspace\/practicas60\/src\/practicas60\/practica14.java"},{"path":"\/programación\/src\/programación","parentWorkspace":"C:\/Users\/1ASIR\/eclipse-workspace","name":"practica6.java","lastModified":1666359433355,"locationURI":"file:\/C:\/Users\/1ASIR\/eclipse-workspace\/programación\/src\/programación\/practica6.java"},{"path":"\/practicas60\/src\/practicas60","parentWorkspace":"C:\/Users\/1ASIR\/eclipse-workspace","name":"practica12.java","lastModified":1666292224223,"locationURI":"file:\/C:\/Users\/1ASIR\/eclipse-workspace\/practicas60\/src\/practicas60\/practica12.java"},{"path":"\/entorno\/src\/entorno","parentWorkspace":"C:\/Users\/1ASIR\/Desktop\/1dam\/ECÑLIPSE\/eclipse-workspace","name":"maquinaExprendedora.java","lastModified":1669058192366,"locationURI":"file:\/C:\/Users\/1ASIR\/Desktop\/1dam\/ECÑLIPSE\/eclipse-workspace\/entorno\/src\/entorno\/maquinaExprendedora.java"},{"path":"\/programación\/src\/programación","parentWorkspace":"C:\/Users\/1ASIR\/eclipse-workspace","name":"practica4.java","lastModified":1666359366725,"locationURI":"file:\/C:\/Users\/1ASIR\/eclipse-workspace\/programación\/src\/programación\/practica4.java"}]}